lms/__init__.py
lms/cmd.py
lms/cmd_safe.py
lms/lms_client.py
lms/lms_req_builder.py
lms/lms_sub_proc.py
lms/run.py
lzl_pytools/__init__.py
lzl_pytools/obj_template.py
lzl_pytools/utils.py
lzl_pytools/apig_sdk/__init__.py
lzl_pytools/apig_sdk/signer.py
lzl_pytools/multi3/__init__.py
lzl_pytools/multi3/aio_task_runner.py
lzl_pytools/multi3/demo.py
lzl_pytools/multi3/multi_process_mng.py
lzl_pytools/multi3/parallel_config.py
lzl_pytools-0.3.3.dist-info/METADATA
lzl_pytools-0.3.3.dist-info/WHEEL
lzl_pytools-0.3.3.dist-info/top_level.txt
lzl_pytools-0.3.3.dist-info/RECORD
