Metadata-Version: 2.1
Name: lzl_pytools
Version: 0.3.3
Summary: a multi run http req tool
Home-page: https://gitee.com/lzlcodex/lzl-pytools.git
Author: lzlcodex
Author-email: yishikong@163.com
Classifier: Programming Language :: Python :: 3
Classifier: License :: OSI Approved :: MIT License
Classifier: Operating System :: OS Independent
Requires-Python: >=3.6
Requires-Dist: six>=1.16.0
Requires-Dist: pyyaml>=6.0.2
Requires-Dist: requests>=2.32.4
Requires-Dist: aiohttp>=3.8.0
Requires-Dist: scikit-learn>=1.2.0
Requires-Dist: faker>=35.2.2
